elasticache_monitor/__init__.py
elasticache_monitor/analyzer.py
elasticache_monitor/bandwidth.py
elasticache_monitor/cli.py
elasticache_monitor/database.py
elasticache_monitor/endpoints.py
elasticache_monitor/monitor.py
elasticache_monitor/reporter.py
elasticache_monitor/utils.py
elasticache_monitor/web/__init__.py
elasticache_monitor/web/cloudwatch.py
elasticache_monitor/web/db.py
elasticache_monitor/web/main.py
elasticache_monitor/web/models.py
elasticache_monitor/web/runner.py
elasticache_monitor/web/signatures.py
elasticache_monitor/web/static/js/url_state.js
elasticache_monitor/web/templates/about.html
elasticache_monitor/web/templates/analysis.html
elasticache_monitor/web/templates/base.html
elasticache_monitor/web/templates/compare.html
elasticache_monitor/web/templates/error.html
elasticache_monitor/web/templates/index.html
elasticache_monitor/web/templates/job_detail.html
elasticache_monitor/web/templates/jobs.html
elasticache_monitor/web/templates/query.html
elasticache_monitor/web/templates/shard_detail.html
elasticache_monitor/web/templates/shard_distribution.html
elasticache_monitor/web/templates/timeline.html
elasticache_monitor-1.0.21.dist-info/METADATA
elasticache_monitor-1.0.21.dist-info/WHEEL
elasticache_monitor-1.0.21.dist-info/entry_points.txt
elasticache_monitor-1.0.21.dist-info/licenses/LICENSE
elasticache_monitor-1.0.21.dist-info/RECORD
