Metadata-Version: 2.4
Name: elasticache-monitor
Version: 1.0.21
Summary: Debug hot shard issues in AWS ElastiCache (Redis/Valkey) clusters with a beautiful web UI
Project-URL: Homepage, https://github.com/k4kratik/elasticache-monitor
Project-URL: Documentation, https://github.com/k4kratik/elasticache-monitor#readme
Project-URL: Repository, https://github.com/k4kratik/elasticache-monitor
Project-URL: Issues, https://github.com/k4kratik/elasticache-monitor/issues
Project-URL: Changelog, https://github.com/k4kratik/elasticache-monitor/blob/main/CHANGELOG.md
Author: Kratik Jain
License: MIT
License-File: LICENSE
Keywords: aws,cluster,debugging,elasticache,hot-shard,monitoring,redis,valkey,web-ui
Classifier: Development Status :: 4 - Beta
Classifier: Environment :: Console
Classifier: Environment :: Web Environment
Classifier: Framework :: FastAPI
Classifier: Intended Audience :: Developers
Classifier: Intended Audience :: System Administrators
Classifier: License :: OSI Approved :: MIT License
Classifier: Operating System :: OS Independent
Classifier: Programming Language :: Python :: 3
Classifier: Programming Language :: Python :: 3.10
Classifier: Programming Language :: Python :: 3.11
Classifier: Programming Language :: Python :: 3.12
Classifier: Topic :: Database
Classifier: Topic :: System :: Monitoring
Classifier: Topic :: System :: Systems Administration
Requires-Python: >=3.10
Requires-Dist: boto3>=1.28.0
Requires-Dist: click>=8.1.0
Requires-Dist: colorama>=0.4.6
Requires-Dist: fastapi>=0.109.0
Requires-Dist: jinja2>=3.1.0
Requires-Dist: python-multipart>=0.0.6
Requires-Dist: pyyaml>=6.0
Requires-Dist: redis>=5.0.0
Requires-Dist: sqlalchemy>=2.0.0
Requires-Dist: tabulate>=0.9.0
Requires-Dist: uvicorn>=0.27.0
Provides-Extra: dev
Requires-Dist: black>=23.0.0; extra == 'dev'
Requires-Dist: pytest>=7.0.0; extra == 'dev'
Requires-Dist: ruff>=0.1.0; extra == 'dev'
